txgpio/__init__.py
txgpio/exceptions.py
txgpio/sysfs.py
txgpio-0.1.1.dist-info/DESCRIPTION.rst
txgpio-0.1.1.dist-info/METADATA
txgpio-0.1.1.dist-info/RECORD
txgpio-0.1.1.dist-info/WHEEL
txgpio-0.1.1.dist-info/metadata.json
txgpio-0.1.1.dist-info/top_level.txt
