Metadata-Version: 2.0
Name: txgpio
Version: 0.1.1
Summary: Twisted-based asynchronous library for using GPIO.
Home-page: UNKNOWN
Author: UNKNOWN
Author-email: UNKNOWN
License: MIT
Platform: UNKNOWN
Requires-Dist: twisted
